citystreetview/__init__.py
citystreetview/baidu.py
citystreetview/equirectangular.py
citystreetview/google.py
citystreetview-1.2.4.dist-info/LICENSE
citystreetview-1.2.4.dist-info/METADATA
citystreetview-1.2.4.dist-info/WHEEL
citystreetview-1.2.4.dist-info/top_level.txt
citystreetview-1.2.4.dist-info/RECORD
