Metadata-Version: 2.1
Name: citystreetview
Version: 1.2.4
Summary: 城市街景爬取工具（百度、Google）
Author-email: Jun Zhang <zhangjun990222@gmail.com>
License: MIT License
Project-URL: Homepage, https://github.com/tsinghua-fib-lab/citystreetview
Project-URL: Repository, https://github.com/tsinghua-fib-lab/citystreetview.git
Project-URL: Issues, https://github.com/tsinghua-fib-lab/citystreetview/issues
Keywords: city,street view
Classifier: Programming Language :: Python :: 3
Classifier: Operating System :: OS Independent
Requires-Python: >=3.8
License-File: LICENSE
Requires-Dist: numpy >=1.24.0
Requires-Dist: opencv-python >=4.8.0.74
Requires-Dist: Pillow >=10.0.0
Requires-Dist: requests >=2.27.0
Requires-Dist: importlib-metadata ; python_version < "3.8"
